rca_batch_calc/__init__.py
rca_batch_calc/data_extract.py
rca_batch_calc/parallel_calc.py
rca_batch_calc/rca_calc.py
rca_batch_calc-0.1.6.dist-info/licenses/LICENSE
rca_batch_calc-0.1.6.dist-info/METADATA
rca_batch_calc-0.1.6.dist-info/WHEEL
rca_batch_calc-0.1.6.dist-info/top_level.txt
rca_batch_calc-0.1.6.dist-info/RECORD
