Metadata-Version: 2.4
Name: rca_batch_calc
Version: 0.1.6
Summary: A tool to calculate Revealed Comparative Advantage (RCA) in batch.
Author: Ning An
License-Expression: MIT
Requires-Python: >=3.7
License-File: LICENSE
Requires-Dist: pandas
Dynamic: license-file
